README.rst
setup.py
nosetests_json_extended_parallel/__init__.py
nosetests_json_extended_parallel/plugin.py
nosetests_json_extended_parallel/sink.py
nosetests_json_extended_parallel/test_plugin.py
nosetests_json_extended_parallel/test_sink.py
nosetests_json_extended_parallel.egg-info/PKG-INFO
nosetests_json_extended_parallel.egg-info/SOURCES.txt
nosetests_json_extended_parallel.egg-info/dependency_links.txt
nosetests_json_extended_parallel.egg-info/entry_points.txt
nosetests_json_extended_parallel.egg-info/not-zip-safe
nosetests_json_extended_parallel.egg-info/top_level.txt