Metadata-Version: 1.1
Name: nosetests-json-extended-parallel
Version: 1.0
Summary: ('Create json logging output for pythonnosetests unittest framework',)
Home-page: https://github.com/ruivapps/nosetests-json-extended-parallel
Author: Rui Li
Author-email: rui.li.spam@gmail.com
License: UNKNOWN
Download-URL: https://github.com/ruivapps/nosetests-json-extended-parallel/tarball/1.0
Platform: UNKNOWN
Classifier: Development Status :: 3 - Alpha
Classifier: Intended Audience :: Developers
Classifier: Operating System :: OS Independent
Classifier: Programming Language :: Python :: 2
Classifier: Programming Language :: Python :: 3
Classifier: Topic :: Software Development :: Testing
